ttsave_cli.py
ttsave/__init__.py
ttsave/__version__.py
ttsave/lib.cp310-win_amd64.pyd
ttsave/js/xbogus-js.min.js
ttsave/utils/xbogus.cp310-win_amd64.pyd
ttsave-2.0.0.dist-info/LICENSE
ttsave-2.0.0.dist-info/METADATA
ttsave-2.0.0.dist-info/WHEEL
ttsave-2.0.0.dist-info/entry_points.txt
ttsave-2.0.0.dist-info/top_level.txt
ttsave-2.0.0.dist-info/RECORD
