Metadata-Version: 2.1
Name: ttsave
Version: 2.0.0
Summary: A simple tool to save TikTok videos
Home-page: https://github.com/FlacSy/ttsave
Author: FlacSy
Author-email: flacsy.tw@gmail.com
License: Apache
License-File: LICENSE
Requires-Dist: requests ==2.32.3
Requires-Dist: cython ==3.0.11
Requires-Dist: PyExecJS ==1.5.1
Requires-Dist: colorama ==0.4.6
Requires-Dist: click ==8.1.7
Requires-Dist: click-shell ==2.1
Requires-Dist: PyYAML ==6.0.2
Requires-Dist: rich ==13.9.4
